haskellian/iterables/__init__.py
haskellian/iterables/basics.py
haskellian/iterables/batching.py
haskellian/iterables/curried.py
haskellian/iterables/generators.py
haskellian/iterables/misc.py
haskellian/iterables/nested.py
haskellian/iterables/slicing.py
haskellian/iterables/zipping.py
haskellian_iterables-0.1.2.dist-info/METADATA
haskellian_iterables-0.1.2.dist-info/WHEEL
haskellian_iterables-0.1.2.dist-info/top_level.txt
haskellian_iterables-0.1.2.dist-info/RECORD
